reporter_su/__init__.py
reporter_su/pbs_reporter.py
reporter_su-0.1.1.dist-info/LICENSE
reporter_su-0.1.1.dist-info/METADATA
reporter_su-0.1.1.dist-info/WHEEL
reporter_su-0.1.1.dist-info/top_level.txt
reporter_su-0.1.1.dist-info/RECORD
