Metadata-Version: 2.1
Name: reporter-su
Version: 0.1.1
Summary: check your task and when it finished, you will receive a email
Home-page: https://github.com/ZeroDesigner/reporter_su.git
Author: Su Jiaqi
Author-email: luskyqi@outlook.com
License: MIT
Keywords: python,email,pbs
Platform: UNKNOWN
Requires-Python: >=3.0
